<?xml version = "1.0" encoding = "UTF-8" standalone = "yes" ?>
<country xmlns:xsi="http://www.w3.org/2001/XMLSchema-instance" xsi:noNamespaceSchemaLocation="country.xsd"
         name="Hungary">
     <economics-data>
		 <GDP value="178,789"/>
		 <PPP value="405,803"/>
		 <population value="9.967308"/>
		 <GDP-growth value="4.58"/>
	</economics-data>
 	
	<!-- Taken from 
  	  	https://en.wikipedia.org/wiki/List_of_countries_by_median_age
    	https://www.worlddata.info/average-bodyheight.php -->
    <characteristics median-age-male="41.5" median-age-female="45.5" 	
				average-male-height="176" average-female-height="162"
	            average-male-weight="88.5" average-female-weight="71.1"/>
		
    <first-name-list>
        <first-name value="Bence" gender="male" />
        <first-name value="Mate" gender="male" />
        <first-name value="Levente" gender="male" />
        <first-name value="Adam" gender="male" />
        <first-name value="David" gender="male" />
        
        <first-name value="Daniel" gender="male" />
        <first-name value="Marcell" gender="male" />
        <first-name value="Balazs" gender="male" />
        <first-name value="Milan" gender="male" />
        <first-name value="Dominik" gender="male" />

        <first-name value="Laszlo" gender="male" />
        <first-name value="Istvan" gender="male" />
        <first-name value="Jozsef" gender="male" />
        <first-name value="Janos" gender="male" />
        <first-name value="Zoltan" gender="male" />
        
        <first-name value="Ferenc" gender="male" />
        <first-name value="Sandor" gender="male" />
        <first-name value="Gabor" gender="male" />
        <first-name value="Tibor" gender="male" />
        <first-name value="Attila" gender="male" />
        

        <first-name value="Laszlo" gender="male" />
        <first-name value="Istvan" gender="male" />
        <first-name value="Jozsef" gender="male" />
        <first-name value="Janos" gender="male" />
        <first-name value="Zoltan" gender="male" />
        
        <first-name value="Ferenc" gender="male" />
        <first-name value="Sandor" gender="male" />
        <first-name value="Gabor" gender="male" />
        <first-name value="Tibor" gender="male" />
        <first-name value="Attila" gender="male" />
        
        
        <first-name value="Hanna" gender="female" />
        <first-name value="Anna" gender="female" />
        <first-name value="Jazmin" gender="female" />
        <first-name value="Lili" gender="female" />
        <first-name value="Zsofia" gender="female" />
        
        <first-name value="Emma" gender="female" />
        <first-name value="Luca" gender="female" />
        <first-name value="Boglarka" gender="female" />
        <first-name value="Zoe" gender="female" />
        <first-name value="Nora" gender="female" />
        
        <first-name value="Lena" gender="female" />
        <first-name value="Olivia" gender="female" />
        <first-name value="Laura" gender="female" />
        <first-name value="Aliz" gender="female" />
        <first-name value="Kamillia" gender="female" />
        
        <first-name value="Sara" gender="female" />
        <first-name value="Szofia" gender="female" />
        <first-name value="Flora" gender="female" />
        <first-name value="Mira" gender="female" />
        <first-name value="Lilien" gender="female" />
                
        <first-name value="Lara" gender="female" />
        <first-name value="Adel" gender="female" />       
 
        <first-name value="Vicktoria" gender="female" />
        <first-name value="Reka" gender="female" />
                
        <first-name value="Katalin" gender="female" />
        <first-name value="Borbala" gender="female" /> 
        
    </first-name-list>
    
    <last-name-list>
        <!-- 20 most common Hungarian surnames -->

        <last-name value="Farkas" />
        <last-name value="Horvath" />
        <last-name value="Kiss" />
        <last-name value="Kovacs" />
        <last-name value="Molnar" />
        
        <last-name value="Nagy" />
        <last-name value="Nemeth" />
        <last-name value="Szabo" />
        <last-name value="Toth" />
        <last-name value="Varga" />
        
        <last-name value="Takacs" />
        <last-name value="Balogh" />
        <last-name value="Papp" />
        <last-name value="Juhasz" />
        <last-name value="Szilagyi" />
        
        <last-name value="Meszaros" />
        <last-name value="Simon" />
        <last-name value="Szucs" />
        <last-name value="Fekete" />
        <last-name value="Torok" />

        
    </last-name-list>
</country>