<?xml version = "1.0" encoding = "UTF-8" standalone = "yes" ?>
<country xmlns:xsi="http://www.w3.org/2001/XMLSchema-instance" xsi:noNamespaceSchemaLocation="country.xsd"
        name="USA">
    <first-name-list>
        <!-- U.S.A., 1-60 male first name http://www2.census.gov/topics/genealogy/1990surnames/dist.male.first -->
        <first-name value="James" gender="male" />
        <first-name value="John" gender="male" />
        <first-name value="Robert" gender="male" />
        <first-name value="Michael" gender="male" />
        <first-name value="William" gender="male" />
        <first-name value="David" gender="male" />
        <first-name value="Richard" gender="male" />
        <first-name value="Charles" gender="male" />
        <first-name value="Joseph" gender="male" />
        <first-name value="Thomas" gender="male" />

        <first-name value="Christopher" gender="male" />
        <first-name value="Daniel" gender="male" />
        <first-name value="Paul" gender="male" />
        <first-name value="Mark" gender="male" />
        <first-name value="Donald" gender="male" />
        <first-name value="George" gender="male" />
        <first-name value="Kenneth" gender="male" />
        <first-name value="Steven" gender="male" />
        <first-name value="Edward" gender="male" />
        <first-name value="Brian" gender="male" />

        <first-name value="Ronald" gender="male" />
        <first-name value="Anthony" gender="male" />
        <first-name value="Kevin" gender="male" />
        <first-name value="Jason" gender="male" />
        <first-name value="Matthew" gender="male" />
        <first-name value="Gary" gender="male" />
        <first-name value="Timothy" gender="male" />
        <first-name value="Jose" gender="male" />
        <first-name value="Larry" gender="male" />
        <first-name value="Jeffrey" gender="male" />

        <first-name value="Frank" gender="male" />
        <first-name value="Scott" gender="male" />
        <first-name value="Eric" gender="male" />
        <first-name value="Stephen" gender="male" />
        <first-name value="Andrew" gender="male" />
        <first-name value="Raymond" gender="male" />
        <first-name value="Gregory" gender="male" />
        <first-name value="Joshua" gender="male" />
        <first-name value="Jerry" gender="male" />
        <first-name value="Dennis" gender="male" />

        <first-name value="Walter" gender="male" />
        <first-name value="Patrick" gender="male" />
        <first-name value="Peter" gender="male" />
        <first-name value="Harold" gender="male" />
        <first-name value="Douglas" gender="male" />
        <first-name value="Henry" gender="male" />
        <first-name value="Carl" gender="male" />
        <first-name value="Arthur" gender="male" />
        <first-name value="Ryan" gender="male" />
        <first-name value="Roger" gender="male" />

        <first-name value="Joe" gender="male" />
        <first-name value="Juan" gender="male" />
        <first-name value="Jack" gender="male" />
        <first-name value="Albert" gender="male" />
        <first-name value="Jonathan" gender="male" />
        <first-name value="Justin" gender="male" />
        <first-name value="Terry" gender="male" />
        <first-name value="Gerald" gender="male" />
        <first-name value="Keith" gender="male" />
        <first-name value="Samuel" gender="male" />


        <first-name value="Willie" gender="male" />
        <first-name value="Ralph" gender="male" />
        <first-name value="Lawrence" gender="male" />
        <first-name value="Nicholas" gender="male" />
        <first-name value="Roy" gender="male" />
        <first-name value="Benjamin" gender="male" />
        <first-name value="Bruce" gender="male" />
        <first-name value="Brandon" gender="male" />
        <first-name value="Adam" gender="male" />
        <first-name value="Harry" gender="male" />


        <first-name value="Fred" gender="male" />
        <first-name value="Wayne" gender="male" />
        <first-name value="Billy" gender="male" />
        <first-name value="Steve" gender="male" />
        <first-name value="Louis" gender="male" />
        <first-name value="Jeremy" gender="male" />
        <first-name value="Aaron" gender="male" />
        <first-name value="Randy" gender="male" />
        <first-name value="Howard" gender="male" />
        <first-name value="Eugene" gender="male" />


        <first-name value="Carlos" gender="male" />
        <first-name value="Russell" gender="male" />
        <first-name value="Robby" gender="male" />
        <first-name value="Victor" gender="male" />
        <first-name value="Martin" gender="male" />
        <first-name value="Ernest" gender="male" />
        <first-name value="Phillip" gender="male" />
        <first-name value="Todd" gender="male" />
        <first-name value="Jesse" gender="male" />
        <first-name value="Craig" gender="male" />


        <first-name value="Alan" gender="male" />
        <first-name value="Shawn" gender="male" />
        <first-name value="Clarence" gender="male" />
        <first-name value="Sean" gender="male" />
        <first-name value="Philip" gender="male" />
        <first-name value="Chris" gender="male" />
        <first-name value="Johnny" gender="male" />
        <first-name value="Earl" gender="male" />
        <first-name value="Jimmy" gender="male" />
        <first-name value="Antonio" gender="male" />

        <first-name value="Danny" gender="male" />
        <first-name value="Bryan" gender="male" />
        <first-name value="Tony" gender="male" />
        <first-name value="Luis" gender="male" />
        <first-name value="Mike" gender="male" />
        <first-name value="Stanley" gender="male" />
        <first-name value="Leonard" gender="male" />
        <first-name value="Nathan" gender="male" />
        <first-name value="Dale" gender="male" />
        <first-name value="Manuel" gender="male" />


        <!--http://www2.census.gov/topics/genealogy/1990surnames/dist.female.first -->
        <first-name value="Mary" gender="female" />
        <first-name value="Patricia" gender="female" />
        <first-name value="Linda" gender="female" />
        <first-name value="Barbara" gender="female" />
        <first-name value="Elizabeth" gender="female" />

        <first-name value="Jennifer" gender="female" />
        <first-name value="Maria" gender="female" />
        <first-name value="Susan" gender="female" />
        <first-name value="Margaret" gender="female" />
        <first-name value="Dorothy" gender="female" />

        <first-name value="Lisa" gender="female" />
        <first-name value="Nancy" gender="female" />
        <first-name value="Karen" gender="female" />
        <first-name value="Betty" gender="female" />
        <first-name value="Helen" gender="female" />

        <first-name value="Sandra" gender="female" />
        <first-name value="Donna" gender="female" />
        <first-name value="Carol" gender="female" />
        <first-name value="Ruth" gender="female" />
        <first-name value="Sharon" gender="female" />

        <first-name value="Michelle" gender="female" />
        <first-name value="Laura" gender="female" />
        <first-name value="Sarah" gender="female" />
        <first-name value="Kimberly" gender="female" />
        <first-name value="Deborah" gender="female" />

        <first-name value="Jessica" gender="female" />
        <first-name value="Shirley" gender="female" />
        <first-name value="Cynthia" gender="female" />
        <first-name value="Angela" gender="female" />
        <first-name value="Melissa" gender="female" />

        <first-name value="Brenda" gender="female" />
        <first-name value="Amy" gender="female" />
        <first-name value="Anna" gender="female" />
        <first-name value="Rebecca" gender="female" />
        <first-name value="Virginia" gender="female" />

        <first-name value="Kathleen" gender="female" />
        <first-name value="Pamela" gender="female" />
        <first-name value="Martha" gender="female" />
        <first-name value="Debra" gender="female" />
        <first-name value="Amanda" gender="female" />

        <first-name value="Stephanie" gender="female" />
        <first-name value="Carolyn" gender="female" />
        <first-name value="Christine" gender="female" />
        <first-name value="Marie" gender="female" />
        <first-name value="Janet" gender="female" />

        <first-name value="Catherine" gender="female" />
        <first-name value="Frances" gender="female" />
        <first-name value="Ann" gender="female" />
        <first-name value="Joyce" gender="female" />
        <first-name value="Diane" gender="female" />

        <first-name value="Alice" gender="female" />
        <first-name value="Julie" gender="female" />
        <first-name value="Heather" gender="female" />
        <first-name value="Teresa" gender="female" />
        <first-name value="Doris" gender="female" />

        <first-name value="Gloria" gender="female" />
        <first-name value="Evelyn" gender="female" />
        <first-name value="Jean" gender="female" />
        <first-name value="Cheryl" gender="female" />
        <first-name value="Mildred" gender="female" />

        <first-name value="Katherine" gender="female" />
        <first-name value="Joan" gender="female" />
        <first-name value="Ashley" gender="female" />
        <first-name value="Judith" gender="female" />
        <first-name value="Rose" gender="female" />

        <first-name value="Janice" gender="female" />
        <first-name value="Kelly" gender="female" />
        <first-name value="Nicole" gender="female" />
        <first-name value="Judy" gender="female" />
        <first-name value="Christina" gender="female" />

        <first-name value="Kathy" gender="female" />
        <first-name value="Theresa" gender="female" />
        <first-name value="Beverly" gender="female" />
        <first-name value="Denise" gender="female" />
        <first-name value="Tammy" gender="female" />

        <first-name value="Irene" gender="female" />
        <first-name value="Jane" gender="female" />
        <first-name value="Lori" gender="female" />
        <first-name value="Rachel" gender="female" />
        <first-name value="Marilyn" gender="female" />

        <first-name value="Andrea" gender="female" />
        <first-name value="Kathryn" gender="female" />
        <first-name value="Louise" gender="female" />
        <first-name value="Sara" gender="female" />
        <first-name value="Anne" gender="female" />

        <first-name value="Jacqueline" gender="female" />
        <first-name value="Wanda" gender="female" />
        <first-name value="Bonnie" gender="female" />
        <first-name value="Julia" gender="female" />
        <first-name value="Ruby" gender="female" />

        <first-name value="Lois" gender="female" />
        <first-name value="Tina" gender="female" />
        <first-name value="Phyllis" gender="female" />
        <first-name value="Norma" gender="female" />
        <first-name value="Paula" gender="female" />

        <first-name value="Diana" gender="female" />
        <first-name value="Annie" gender="female" />
        <first-name value="Lillian" gender="female" />
        <first-name value="Emily" gender="female" />
        <first-name value="Robin" gender="female" />

        <first-name value="Peggy" gender="female" />
        <first-name value="Crystal" gender="female" />
        <first-name value="Gladys" gender="female" />
        <first-name value="Rita" gender="female" />
        <first-name value="Dawn" gender="female" />
    </first-name-list>
    <last-name-list>
        <!-- http://www.census.gov/topics/population/genealogy/data/2000_surnames.html -->
        <!-- 1 to 34 -->
        <last-name value="Allen" />
        <last-name value="Anderson" />
        <last-name value="Brown" />
        <last-name value="Clark" />
        <last-name value="Davis" />

        <last-name value="Garcia" />
        <last-name value="Gonzalez" />
        <last-name value="Hall" />
        <last-name value="Harris" />
        <last-name value="Hernandez" />

        <last-name value="Jackson" />
        <last-name value="Johnson" />
        <last-name value="Jones" />
        <last-name value="Lee" />
        <last-name value="Lewis" />

        <last-name value="Lopez" />
        <last-name value="Martin" />
        <last-name value="Martinez" />
        <last-name value="Miller" />
        <last-name value="Moore" />

        <last-name value="Perez" />
        <last-name value="Robinson" />
        <last-name value="Roriguez" />
        <last-name value="Sanchez" />
        <last-name value="Smith" />

        <last-name value="Taylor" />
        <last-name value="Thomas" />
        <last-name value="Thompson" />
        <last-name value="Walker" />
        <last-name value="White" />

        <last-name value="Williams" />
        <last-name value="Wilson" />
        <last-name value="Young" />

        <!-- 36 to 80 -->
        <last-name value="Wright" />
        <last-name value="King" />
        <last-name value="Scott" />
        <last-name value="Green" />
        <last-name value="Baker" />

        <last-name value="Adams" />
        <last-name value="Nelson" />
        <last-name value="Hill" />
        <last-name value="Ramirez" />
        <last-name value="Campbell" />

        <last-name value="Mitchell" />
        <last-name value="Roberts" />
        <last-name value="Carter" />
        <last-name value="Phillips" />
        <last-name value="Evans" />

        <last-name value="Turner" />
        <last-name value="Torres" />
        <last-name value="Parker" />
        <last-name value="Collins" />
        <last-name value="Edwards" />

        <last-name value="Stewart" />
        <last-name value="Flores" />
        <last-name value="Morris" />
        <last-name value="Nguyen" />
        <last-name value="Murphy" />

        <last-name value="Rivera" />
        <last-name value="Cook" />
        <last-name value="Rogers" />
        <last-name value="Morgan" />
        <last-name value="Peterson" />

        <last-name value="Cooper" />
        <last-name value="Reed" />
        <last-name value="Bailey" />
        <last-name value="Bell" />
        <last-name value="Gomez" />

        <last-name value="Kelly" />
        <last-name value="Howard" />
        <last-name value="Ward" />
        <last-name value="Cox" />
        <last-name value="Diaz" />

        <last-name value="Richardson" />
        <last-name value="Wood" />
        <last-name value="Watson" />
        <last-name value="Brooks" />
        <last-name value="Bennett" />
    </last-name-list>
</country>
